{
    "@context": [
        "https://www.w3.org/2018/credentials/v1",
        "http://w3id.org/gaia-x/participant",
        "https://registry.gaia-x.eu/v2206/api/shape/files?file=participant&type=ttl"
    ],
    "type": [
        "VerifiableCredential",
        "LegalPerson"
    ],
    "id": "https://delta-dao.com/.well-known/participantDatarella.json",
    "issuer": "did:web:delta-dao.com",
    "issuanceDate": "2022-09-23T23:23:23.235Z",
    "credentialSubject": {
        "id": "https://delta-dao.com/.well-known/participantDatarella.json",
        "gx-participant:legalName": "Datarella GmbH",
        "gx-participant:website": "https://datarella.com/",
        "gx-participant:registrationNumber": {
            "gx-participant:registrationNumberType": "EUID",
            "gx-participant:registrationNumberNumber": "DED2601V.HRB207851"
        },
        "gx-participant:blockchainAccountId": "0x0aec046a558F13Ff18aAEc5E6f76084185358cdf",
        "gx-participant:headquarterAddress": {
            "gx-participant:addressCountryCode": "DE",
            "gx-participant:addressCode": "DE-BY",
            "gx-participant:streetAddress": "Oskar-von-Miller-Ring 36",
            "gx-participant:postalCode": "80333",
            "gx-participant:locality": "Munich"
        },
        "gx-participant:legalAddress": {
            "gx-participant:addressCountryCode": "DE",
            "gx-participant:addressCode": "DE-BY",
            "gx-participant:streetAddress": "Oskar-von-Miller-Ring 36",
            "gx-participant:postalCode": "80333",
            "gx-participant:locality": "Munich"
        },
        "gx-participant:termsAndConditions": "70c1d713215f95191a11d38fe2341faed27d19e083917bc8732ca4fea4976700"
    }
}